ml4fmri/__init__.py
ml4fmri/cvreport.py
ml4fmri/utils.py
ml4fmri/models/BNT.py
ml4fmri/models/BolT.py
ml4fmri/models/BrainNetCNN.py
ml4fmri/models/DICE.py
ml4fmri/models/FBNetGen.py
ml4fmri/models/Glacier.py
ml4fmri/models/LR.py
ml4fmri/models/LSTM.py
ml4fmri/models/MILC.py
ml4fmri/models/Transformer.py
ml4fmri/models/__init__.py
ml4fmri/models/helper_functions.py
ml4fmri/models/meanLSTM.py
ml4fmri/models/meanMLP.py
ml4fmri/models/meanTransformer.py
ml4fmri-1.0.5.dist-info/METADATA
ml4fmri-1.0.5.dist-info/WHEEL
ml4fmri-1.0.5.dist-info/top_level.txt
ml4fmri-1.0.5.dist-info/RECORD
