Metadata-Version: 2.4
Name: ml4fmri
Version: 1.0.5
Summary: Machine learning models for fMRI classification
Author: Pavel Popov
License: MIT
Project-URL: Homepage, https://github.com/neuroneural/meanMLP/tree/ml4fmri
Requires-Python: >=3.9
Requires-Dist: torch>=2.1
Requires-Dist: numpy>=1.24
Requires-Dist: matplotlib>=3.7
Requires-Dist: scikit-learn>=1.3
Requires-Dist: pandas>=1.5
Provides-Extra: dev
Requires-Dist: pytest; extra == "dev"
Requires-Dist: ipykernel; extra == "dev"
